aldryn_events/__init__.py
aldryn_events/admin.py
aldryn_events/apps.py
aldryn_events/cms_appconfig.py
aldryn_events/cms_apps.py
aldryn_events/cms_menus.py
aldryn_events/cms_plugins.py
aldryn_events/cms_toolbars.py
aldryn_events/cms_wizards.py
aldryn_events/conf.py
aldryn_events/forms.py
aldryn_events/managers.py
aldryn_events/models.py
aldryn_events/search_indexes.py
aldryn_events/urls.py
aldryn_events/utils.py
aldryn_events/views.py
aldryn_events/boilerplates/bootstrap3/static/js/addons/cl.events.js
aldryn_events/boilerplates/bootstrap3/static/js/libs/jquery.min.js
aldryn_events/boilerplates/bootstrap3/templates/aldryn_events/base.html
aldryn_events/boilerplates/bootstrap3/templates/aldryn_events/events_detail.html
aldryn_events/boilerplates/bootstrap3/templates/aldryn_events/events_list.html
aldryn_events/boilerplates/bootstrap3/templates/aldryn_events/fullwidth.html
aldryn_events/boilerplates/bootstrap3/templates/aldryn_events/two_column.html
aldryn_events/boilerplates/bootstrap3/templates/aldryn_events/emails/manager_confirmation.body.txt
aldryn_events/boilerplates/bootstrap3/templates/aldryn_events/emails/manager_confirmation.subject.txt
aldryn_events/boilerplates/bootstrap3/templates/aldryn_events/emails/registrant_confirmation.body.txt
aldryn_events/boilerplates/bootstrap3/templates/aldryn_events/emails/registrant_confirmation.subject.txt
aldryn_events/boilerplates/bootstrap3/templates/aldryn_events/includes/calendar.html
aldryn_events/boilerplates/bootstrap3/templates/aldryn_events/includes/calendar_table.html
aldryn_events/boilerplates/bootstrap3/templates/aldryn_events/includes/event.html
aldryn_events/boilerplates/bootstrap3/templates/aldryn_events/includes/pagination.html
aldryn_events/boilerplates/bootstrap3/templates/aldryn_events/includes/registration.html
aldryn_events/boilerplates/bootstrap3/templates/aldryn_events/plugins/calendar.html
aldryn_events-3.0.0.dist-info/DESCRIPTION.rst
aldryn_events-3.0.0.dist-info/METADATA
aldryn_events-3.0.0.dist-info/RECORD
aldryn_events-3.0.0.dist-info/WHEEL
aldryn_events-3.0.0.dist-info/metadata.json
aldryn_events-3.0.0.dist-info/top_level.txt
