Metadata-Version: 2.0
Name: aldryn-events
Version: 3.0.0
Summary: An events app for Aldryn
Home-page: https://github.com/aldryn/aldryn-events
Author: Divio AG
Author-email: info@divio.ch
License: LICENSE.txt
Platform: OS Independent
Classifier: Development Status :: 5 - Production/Stable
Classifier: Environment :: Web Environment
Classifier: Framework :: Django
Classifier: Framework :: Django :: 1.8
Classifier: Framework :: Django :: 1.9
Classifier: Framework :: Django :: 1.10
Classifier: Framework :: Django :: 1.11
Classifier: Intended Audience :: Developers
Classifier: License :: OSI Approved :: BSD License
Classifier: Operating System :: OS Independent
Classifier: Programming Language :: Python
Classifier: Programming Language :: Python :: 2.7
Classifier: Programming Language :: Python :: 3.3
Classifier: Programming Language :: Python :: 3.4
Classifier: Programming Language :: Python :: 3.5
Classifier: Programming Language :: Python :: 3.6
Classifier: Topic :: Internet :: WWW/HTTP :: Dynamic Content
Classifier: Topic :: Software Development
Classifier: Topic :: Software Development :: Libraries :: Application Frameworks
Requires-Dist: Django (>=1.8,<2)
Requires-Dist: aldryn-apphooks-config (>=0.4.0)
Requires-Dist: aldryn-boilerplates
Requires-Dist: aldryn-common (>=0.0.6)
Requires-Dist: aldryn-translation-tools (>=0.2.1)
Requires-Dist: django-appconf
Requires-Dist: django-appdata (<0.2)
Requires-Dist: django-bootstrap3
Requires-Dist: django-cms (>=3.4)
Requires-Dist: django-extended-choices
Requires-Dist: django-filer
Requires-Dist: django-parler (>=1.6.1)
Requires-Dist: django-sortedm2m (>=1.2.2)
Requires-Dist: django-standard-form (>=1.1.1)
Requires-Dist: django-tablib
Requires-Dist: djangocms-text-ckeditor
Requires-Dist: python-dateutil
Requires-Dist: six
